django_semantic_mediawiki/__init__.py
django_semantic_mediawiki/models.py
django_semantic_mediawiki-0.1.dist-info/DESCRIPTION.rst
django_semantic_mediawiki-0.1.dist-info/METADATA
django_semantic_mediawiki-0.1.dist-info/pydist.json
django_semantic_mediawiki-0.1.dist-info/RECORD
django_semantic_mediawiki-0.1.dist-info/top_level.txt
django_semantic_mediawiki-0.1.dist-info/WHEEL
