Metadata-Version: 2.0
Name: django-semantic-mediawiki
Version: 0.1
Summary: Use the semantic mediawiki API as django models
Home-page: https://github.com/C4ptainCrunch/django-semantic-mediawiki
Author: Nikita Marchant
Author-email: nikita.marchant@gmail.com
License: UNKNOWN
Download-URL: https://github.com/C4ptainCrunch/django-semantic-mediawiki/tarball/0.1
Keywords: django,mediawiki,api,manager,queryset,orm
Platform: UNKNOWN
Classifier: Development Status :: 3 - Alpha
Classifier: Framework :: Django
Classifier: Intended Audience :: Developers
Classifier: License :: OSI Approved :: Apache Software License
Classifier: Programming Language :: Python :: 2 :: Only
Classifier: Topic :: Database
Classifier: Topic :: Internet :: WWW/HTTP :: Dynamic Content
Classifier: Topic :: Software Development :: Libraries :: Python Modules
Requires-Dist: django
Requires-Dist: requests
